git_guardian/__init__.py
git_guardian/cli.py
git_guardian/hook_manager.py
git_guardian/reporter.py
git_guardian/scanner.py
git_guardian_cli-1.0.2.dist-info/METADATA
git_guardian_cli-1.0.2.dist-info/WHEEL
git_guardian_cli-1.0.2.dist-info/entry_points.txt
git_guardian_cli-1.0.2.dist-info/top_level.txt
git_guardian_cli-1.0.2.dist-info/RECORD
