Metadata-Version: 2.1
Name: git-guardian-cli
Version: 1.0.2
Summary: A CLI tool to scan Git repositories for sensitive information
Home-page: https://github.com/000xs/git-guardian-cli
Author: 000x
Author-email: sithumss9122@gmail.com
Classifier: Programming Language :: Python :: 3
Classifier: License :: OSI Approved :: MIT License
Classifier: Operating System :: OS Independent
Requires-Python: >=3.7
Requires-Dist: click>=8.0.0
Requires-Dist: gitpython>=3.1.0
